actingweb/__init__.py
actingweb/actor.py
actingweb/attribute.py
actingweb/auth.py
actingweb/aw_proxy.py
actingweb/aw_web_request.py
actingweb/config.py
actingweb/constants.py
actingweb/db/__init__.py
actingweb/db/dynamodb/__init__.py
actingweb/db/dynamodb/actor.py
actingweb/db/dynamodb/attribute.py
actingweb/db/dynamodb/peertrustee.py
actingweb/db/dynamodb/property.py
actingweb/db/dynamodb/property_lookup.py
actingweb/db/dynamodb/subscription.py
actingweb/db/dynamodb/subscription_diff.py
actingweb/db/dynamodb/trust.py
actingweb/db/postgresql/__init__.py
actingweb/db/postgresql/actor.py
actingweb/db/postgresql/alembic.ini
actingweb/db/postgresql/attribute.py
actingweb/db/postgresql/connection.py
actingweb/db/postgresql/migrations/README
actingweb/db/postgresql/migrations/env.py
actingweb/db/postgresql/migrations/script.py.mako
actingweb/db/postgresql/migrations/versions/3307e3616c5e_initial_postgresql_schema.py
actingweb/db/postgresql/migrations/versions/70d60420526_add_property_lookup_table.py
actingweb/db/postgresql/peertrustee.py
actingweb/db/postgresql/property.py
actingweb/db/postgresql/property_lookup.py
actingweb/db/postgresql/schema.py
actingweb/db/postgresql/subscription.py
actingweb/db/postgresql/subscription_diff.py
actingweb/db/postgresql/trust.py
actingweb/db/protocols.py
actingweb/db/utils.py
actingweb/handlers/__init__.py
actingweb/handlers/actions.py
actingweb/handlers/async_actions.py
actingweb/handlers/async_methods.py
actingweb/handlers/async_trust.py
actingweb/handlers/base_handler.py
actingweb/handlers/bot.py
actingweb/handlers/callback_oauth.py
actingweb/handlers/callbacks.py
actingweb/handlers/devtest.py
actingweb/handlers/email_verification.py
actingweb/handlers/factory.py
actingweb/handlers/mcp.py
actingweb/handlers/meta.py
actingweb/handlers/methods.py
actingweb/handlers/oauth2_callback.py
actingweb/handlers/oauth2_endpoints.py
actingweb/handlers/oauth2_spa.py
actingweb/handlers/oauth_email.py
actingweb/handlers/properties.py
actingweb-3.9.2.dist-info/LICENSE.rst
actingweb-3.9.2.dist-info/METADATA
actingweb-3.9.2.dist-info/WHEEL
actingweb-3.9.2.dist-info/RECORD
