Metadata-Version: 2.1
Name: actingweb
Version: 3.9.2
Summary: The official ActingWeb library
Home-page: http://actingweb.org
License: BSD
Keywords: actingweb,distributed,microservices,rest,api
Author: Greger Wedel
Author-email: support@greger.io
Maintainer: Greger Wedel
Maintainer-email: support@greger.io
Requires-Python: >=3.11,<4.0
Classifier: Development Status :: 5 - Production/Stable
Classifier: Intended Audience :: Developers
Classifier: License :: OSI Approved :: BSD License
Classifier: License :: Other/Proprietary License
Classifier: Programming Language :: Python :: 3
Classifier: Programming Language :: Python :: 3.11
Classifier: Programming Language :: Python :: 3.12
Classifier: Topic :: Internet :: WWW/HTTP :: HTTP Servers
Classifier: Topic :: Software Development :: Libraries :: Python Modules
Classifier: Topic :: System :: Distributed Computing
Provides-Extra: all
Provides-Extra: fastapi
Provides-Extra: flask
Provides-Extra: mcp
Provides-Extra: postgresql
Requires-Dist: alembic (>=1.13.0,<2.0.0) ; extra == "postgresql" or extra == "all"
Requires-Dist: boto3 (>=1.40.6,<2.0.0)
Requires-Dist: cryptography (>=46.0.3,<47.0.0)
Requires-Dist: fastapi (>=0.128.0,<0.129.0) ; extra == "fastapi" or extra == "all"
Requires-Dist: flask (>=3.1.1,<4.0.0) ; extra == "flask" or extra == "all"
Requires-Dist: httpx (>=0.28.0,<0.29.0)
Requires-Dist: jinja2 (>=3.0.0,<4.0.0) ; extra == "flask" or extra == "fastapi" or extra == "all"
Requires-Dist: mcp (>=1.23.0,<2.0.0) ; extra == "mcp" or extra == "all"
Requires-Dist: oauthlib (>=3.2.0,<4.0.0)
Requires-Dist: psycopg[binary,pool] (>=3.1.0,<4.0.0) ; extra == "postgresql" or extra == "all"
Requires-Dist: pydantic (>=2.0.0,<3.0.0) ; extra == "fastapi" or extra == "all"
Requires-Dist: pynamodb (>=6.0.0,<7.0.0)
Requires-Dist: requests (>=2.31.0,<3.0.0)
Requires-Dist: sqlalchemy (>=2.0.0,<3.0.0) ; extra == "postgresql" or extra == "all"
Requires-Dist: typing-extensions (>=4.0.0,<5.0.0)
Requires-Dist: uvicorn (>=0.40.0,<0.41.0) ; extra == "fastapi" or extra == "all"
Requires-Dist: werkzeug (>=3.1.3,<4.0.0) ; extra == "flask" or extra == "all"
Project-URL: Documentation, http://actingweb.readthedocs.io
Project-URL: Repository, https://github.com/actingweb/actingweb
